SBART/Base_Models/Frame.py
SBART/Base_Models/RV_routine.py
SBART/Base_Models/Sampler_Model.py
SBART/Base_Models/TemplateFramework.py
SBART/Base_Models/Template_Model.py
SBART/Base_Models/UnitModel.py
SBART/Base_Models/__init__.py
SBART/Components/Modelling.py
SBART/Components/Spectral_Normalization.py
SBART/Components/SpectrumComponent.py
SBART/Components/__init__.py
SBART/DataUnits/ClassicalUnit.py
SBART/DataUnits/SpecNormUnit.py
SBART/DataUnits/__init__.py
SBART/Instruments/ESPRESSO.py
SBART/Instruments/HARPS.py
SBART/Instruments/__init__.py
SBART/Masks/Mask_class.py
SBART/Masks/__init__.py
SBART/ModelParameters/Model.py
SBART/ModelParameters/Parameter.py
SBART/ModelParameters/__init__.py
SBART/Quality_Control/__init__.py
SBART/Quality_Control/activity_indicators.py
SBART/Quality_Control/ensure_value_in_limits.py
SBART/Quality_Control/outlier_detection.py
SBART/Samplers/Laplace_approx.py
SBART/Samplers/MCMC_sampler.py
SBART/Samplers/SbartBaseSampler.py
SBART/Samplers/WindowSampler.py
SBART/Samplers/__init__.py
SBART/Samplers/chi_squared_sampler.py
SBART/__init__.py
SBART/data_objects/DataClass.py
SBART/data_objects/MetaData.py
SBART/data_objects/RV_cube.py
SBART/data_objects/RV_outputs.py
SBART/data_objects/Target.py
SBART/data_objects/__init__.py
SBART/outside_tools/Load_RVoutputs.py
SBART/outside_tools/create_logger.py
SBART/outside_tools/run_SBART_from_config_dict.py
SBART/outside_tools/run_SBART_from_yaml.py
SBART/resources/atmosphere_profiles/ESPRESSO_atmosphere_profile.txt
SBART/resources/atmosphere_profiles/README.md
SBART/resources/atmosphere_profiles/gdas_profiles_C-70.4-24.6.tar.gz
SBART/resources/header_file.json
SBART/rv_calculation/RV_Bayesian/RV_Bayesian.py
SBART/rv_calculation/RV_Bayesian/__init__.py
SBART/rv_calculation/RV_Bayesian/target_function.py
SBART/rv_calculation/__init__.py
SBART/rv_calculation/rv_stepping/RV_step.py
SBART/rv_calculation/rv_stepping/__init__.py
SBART/rv_calculation/rv_stepping/target_function.py
sbart-0.2.0.dist-info/LICENSE
sbart-0.2.0.dist-info/WHEEL
sbart-0.2.0.dist-info/METADATA
sbart-0.2.0.dist-info/RECORD
