Metadata-Version: 2.1
Name: sbart
Version: 0.2.0
Summary: semi-Bayesian Radial Velocities
Author: Kamuish
Author-email: andremiguel952@gmail.com
Requires-Python: >=3.8,<4.0
Classifier: Programming Language :: Python :: 3
Classifier: Programming Language :: Python :: 3.10
Classifier: Programming Language :: Python :: 3.8
Classifier: Programming Language :: Python :: 3.9
Requires-Dist: Cython (>=0.29.28,<0.30.0)
Requires-Dist: PyYAML (>=6.0,<7.0)
Requires-Dist: astropy (>=5.0.4,<6.0.0)
Requires-Dist: astroquery (>=0.4.6,<0.5.0)
Requires-Dist: corner (>=2.2.1,<3.0.0)
Requires-Dist: emcee (>=3.1.1,<4.0.0)
Requires-Dist: eniric (>=0.5.1,<0.6.0)
Requires-Dist: iCCF (>=0.3.10,<0.4.0)
Requires-Dist: loguru (>=0.6.0,<0.7.0)
Requires-Dist: matplotlib (>=3.5.1,<4.0.0)
Requires-Dist: numpy (>=1.22.3,<2.0.0)
Requires-Dist: python-dateutil (>=2.8.2,<3.0.0)
Requires-Dist: requests (>=2.27.1,<3.0.0)
Requires-Dist: tabletexifier (>=0.1.9,<0.2.0)
Requires-Dist: tqdm (>=4.64.0,<5.0.0)
Requires-Dist: ujson (>=5.4.0,<6.0.0)
